[
  {
    "actual_time": 1646415379,
    "alliances": {
      "blue": {
        "dq_team_keys": [],
        "score": 41,
        "surrogate_team_keys": [],
        "team_keys": [
          "frc7913",
          "frc8046",
          "frc95"
        ]
      },
      "red": {
        "dq_team_keys": [],
        "score": 9,
        "surrogate_team_keys": [],
        "team_keys": [
          "frc1277",
          "frc1721",
          "frc5491"
        ]
      }
    },
    "comp_level": "qm",
    "event_key": "2022nhgrs",
    "key": "2022nhgrs_qm10",
    "match_number": 10,
    "post_result_time": 1646415654,
    "predicted_time": 1646415470,
    "score_breakdown": {
      "blue": {
        "adjustPoints": 0,
        "autoCargoLowerBlue": 0,
        "autoCargoLowerFar": 0,
        "autoCargoLowerNear": 1,
        "autoCargoLowerRed": 0,
        "autoCargoPoints": 2,
        "autoCargoTotal": 1,
        "autoCargoUpperBlue": 0,
        "autoCargoUpperFar": 0,
        "autoCargoUpperNear": 0,
        "autoCargoUpperRed": 0,
        "autoPoints": 8,
        "autoTaxiPoints": 6,
        "cargoBonusRankingPoint": false,
        "endgamePoints": 15,
        "endgameRobot1": "None",
        "endgameRobot2": "None",
        "endgameRobot3": "Traversal",
        "foulCount": 0,
        "foulPoints": 0,
        "hangarBonusRankingPoint": false,
        "matchCargoTotal": 17,
        "quintetAchieved": false,
        "rp": 2,
        "taxiRobot1": "Yes",
        "taxiRobot2": "Yes",
        "taxiRobot3": "Yes",
        "techFoulCount": 0,
        "teleopCargoLowerBlue": 4,
        "teleopCargoLowerFar": 3,
        "teleopCargoLowerNear": 4,
        "teleopCargoLowerRed": 3,
        "teleopCargoPoints": 18,
        "teleopCargoTotal": 16,
        "teleopCargoUpperBlue": 1,
        "teleopCargoUpperFar": 1,
        "teleopCargoUpperNear": 0,
        "teleopCargoUpperRed": 0,
        "teleopPoints": 33,
        "totalPoints": 41
      },
      "red": {
        "adjustPoints": 0,
        "autoCargoLowerBlue": 0,
        "autoCargoLowerFar": 0,
        "autoCargoLowerNear": 0,
        "autoCargoLowerRed": 0,
        "autoCargoPoints": 4,
        "autoCargoTotal": 1,
        "autoCargoUpperBlue": 0,
        "autoCargoUpperFar": 0,
        "autoCargoUpperNear": 1,
        "autoCargoUpperRed": 0,
        "autoPoints": 6,
        "autoTaxiPoints": 2,
        "cargoBonusRankingPoint": false,
        "endgamePoints": 0,
        "endgameRobot1": "None",
        "endgameRobot2": "None",
        "endgameRobot3": "None",
        "foulCount": 0,
        "foulPoints": 0,
        "hangarBonusRankingPoint": false,
        "matchCargoTotal": 4,
        "quintetAchieved": false,
        "rp": 0,
        "taxiRobot1": "No",
        "taxiRobot2": "No",
        "taxiRobot3": "Yes",
        "techFoulCount": 0,
        "teleopCargoLowerBlue": 2,
        "teleopCargoLowerFar": 1,
        "teleopCargoLowerNear": 0,
        "teleopCargoLowerRed": 0,
        "teleopCargoPoints": 3,
        "teleopCargoTotal": 3,
        "teleopCargoUpperBlue": 0,
        "teleopCargoUpperFar": 0,
        "teleopCargoUpperNear": 0,
        "teleopCargoUpperRed": 0,
        "teleopPoints": 3,
        "totalPoints": 9
      }
    },
    "set_number": 1,
    "time": 1646413920,
    "videos": [
      {
        "key": "gTpMqf8LK-k",
        "type": "youtube"
      }
    ],
    "winning_alliance": "blue"
  },
  {
    "actual_time": 1646498686,
    "alliances": {
      "blue": {
        "dq_team_keys": [],
        "score": 58,
        "surrogate_team_keys": [],
        "team_keys": [
          "frc4909",
          "frc1768",
          "frc5491"
        ]
      },
      "red": {
        "dq_team_keys": [],
        "score": 92,
        "surrogate_team_keys": [],
        "team_keys": [
          "frc3467",
          "frc6328",
          "frc151"
        ]
      }
    },
    "comp_level": "qm",
    "event_key": "2022nhgrs",
    "key": "2022nhgrs_qm16",
    "match_number": 16,
    "post_result_time": 1646498869,
    "predicted_time": 1646421018,
    "score_breakdown": {
      "blue": {
        "adjustPoints": 0,
        "autoCargoLowerBlue": 0,
        "autoCargoLowerFar": 0,
        "autoCargoLowerNear": 0,
        "autoCargoLowerRed": 0,
        "autoCargoPoints": 12,
        "autoCargoTotal": 3,
        "autoCargoUpperBlue": 1,
        "autoCargoUpperFar": 1,
        "autoCargoUpperNear": 0,
        "autoCargoUpperRed": 1,
        "autoPoints": 16,
        "autoTaxiPoints": 4,
        "cargoBonusRankingPoint": false,
        "endgamePoints": 12,
        "endgameRobot1": "Mid",
        "endgameRobot2": "Mid",
        "endgameRobot3": "None",
        "foulCount": 0,
        "foulPoints": 0,
        "hangarBonusRankingPoint": false,
        "matchCargoTotal": 18,
        "quintetAchieved": false,
        "rp": 0,
        "taxiRobot1": "Yes",
        "taxiRobot2": "Yes",
        "taxiRobot3": "No",
        "techFoulCount": 0,
        "teleopCargoLowerBlue": 0,
        "teleopCargoLowerFar": 0,
        "teleopCargoLowerNear": 0,
        "teleopCargoLowerRed": 0,
        "teleopCargoPoints": 30,
        "teleopCargoTotal": 15,
        "teleopCargoUpperBlue": 2,
        "teleopCargoUpperFar": 5,
        "teleopCargoUpperNear": 2,
        "teleopCargoUpperRed": 6,
        "teleopPoints": 42,
        "totalPoints": 58
      },
      "red": {
        "adjustPoints": 0,
        "autoCargoLowerBlue": 0,
        "autoCargoLowerFar": 0,
        "autoCargoLowerNear": 0,
        "autoCargoLowerRed": 0,
        "autoCargoPoints": 16,
        "autoCargoTotal": 4,
        "autoCargoUpperBlue": 1,
        "autoCargoUpperFar": 2,
        "autoCargoUpperNear": 0,
        "autoCargoUpperRed": 1,
        "autoPoints": 20,
        "autoTaxiPoints": 4,
        "cargoBonusRankingPoint": true,
        "endgamePoints": 30,
        "endgameRobot1": "None",
        "endgameRobot2": "Traversal",
        "endgameRobot3": "Traversal",
        "foulCount": 0,
        "foulPoints": 0,
        "hangarBonusRankingPoint": true,
        "matchCargoTotal": 25,
        "quintetAchieved": false,
        "rp": 4,
        "taxiRobot1": "No",
        "taxiRobot2": "Yes",
        "taxiRobot3": "Yes",
        "techFoulCount": 0,
        "teleopCargoLowerBlue": 0,
        "teleopCargoLowerFar": 0,
        "teleopCargoLowerNear": 0,
        "teleopCargoLowerRed": 0,
        "teleopCargoPoints": 42,
        "teleopCargoTotal": 21,
        "teleopCargoUpperBlue": 9,
        "teleopCargoUpperFar": 3,
        "teleopCargoUpperNear": 6,
        "teleopCargoUpperRed": 3,
        "teleopPoints": 72,
        "totalPoints": 92
      }
    },
    "set_number": 1,
    "time": 1646420340,
    "videos": [
      {
        "key": "lDE-p8By-6w",
        "type": "youtube"
      },
      {
        "key": "dW8QC5HuHVU",
        "type": "youtube"
      },
      {
        "key": "oUhn_UmF7RA",
        "type": "youtube"
      }
    ],
    "winning_alliance": "red"
  },
  {
    "actual_time": 1646425915,
    "alliances": {
      "blue": {
        "dq_team_keys": [],
        "score": 31,
        "surrogate_team_keys": [],
        "team_keys": [
          "frc4925",
          "frc8013",
          "frc6763"
        ]
      },
      "red": {
        "dq_team_keys": [],
        "score": 44,
        "surrogate_team_keys": [],
        "team_keys": [
          "frc95",
          "frc88",
          "frc5491"
        ]
      }
    },
    "comp_level": "qm",
    "event_key": "2022nhgrs",
    "key": "2022nhgrs_qm25",
    "match_number": 25,
    "post_result_time": 1646426108,
    "predicted_time": 1646426001,
    "score_breakdown": {
      "blue": {
        "adjustPoints": 0,
        "autoCargoLowerBlue": 1,
        "autoCargoLowerFar": 0,
        "autoCargoLowerNear": 0,
        "autoCargoLowerRed": 0,
        "autoCargoPoints": 6,
        "autoCargoTotal": 2,
        "autoCargoUpperBlue": 0,
        "autoCargoUpperFar": 0,
        "autoCargoUpperNear": 0,
        "autoCargoUpperRed": 1,
        "autoPoints": 10,
        "autoTaxiPoints": 4,
        "cargoBonusRankingPoint": false,
        "endgamePoints": 6,
        "endgameRobot1": "None",
        "endgameRobot2": "Mid",
        "endgameRobot3": "None",
        "foulCount": 0,
        "foulPoints": 0,
        "hangarBonusRankingPoint": false,
        "matchCargoTotal": 12,
        "quintetAchieved": false,
        "rp": 0,
        "taxiRobot1": "Yes",
        "taxiRobot2": "No",
        "taxiRobot3": "Yes",
        "techFoulCount": 0,
        "teleopCargoLowerBlue": 2,
        "teleopCargoLowerFar": 0,
        "teleopCargoLowerNear": 0,
        "teleopCargoLowerRed": 3,
        "teleopCargoPoints": 15,
        "teleopCargoTotal": 10,
        "teleopCargoUpperBlue": 2,
        "teleopCargoUpperFar": 1,
        "teleopCargoUpperNear": 0,
        "teleopCargoUpperRed": 2,
        "teleopPoints": 21,
        "totalPoints": 31
      },
      "red": {
        "adjustPoints": 0,
        "autoCargoLowerBlue": 0,
        "autoCargoLowerFar": 0,
        "autoCargoLowerNear": 0,
        "autoCargoLowerRed": 0,
        "autoCargoPoints": 12,
        "autoCargoTotal": 3,
        "autoCargoUpperBlue": 0,
        "autoCargoUpperFar": 1,
        "autoCargoUpperNear": 1,
        "autoCargoUpperRed": 1,
        "autoPoints": 14,
        "autoTaxiPoints": 2,
        "cargoBonusRankingPoint": false,
        "endgamePoints": 10,
        "endgameRobot1": "None",
        "endgameRobot2": "None",
        "endgameRobot3": "High",
        "foulCount": 0,
        "foulPoints": 0,
        "hangarBonusRankingPoint": false,
        "matchCargoTotal": 13,
        "quintetAchieved": false,
        "rp": 2,
        "taxiRobot1": "No",
        "taxiRobot2": "No",
        "taxiRobot3": "Yes",
        "techFoulCount": 0,
        "teleopCargoLowerBlue": 0,
        "teleopCargoLowerFar": 0,
        "teleopCargoLowerNear": 0,
        "teleopCargoLowerRed": 0,
        "teleopCargoPoints": 20,
        "teleopCargoTotal": 10,
        "teleopCargoUpperBlue": 4,
        "teleopCargoUpperFar": 2,
        "teleopCargoUpperNear": 2,
        "teleopCargoUpperRed": 2,
        "teleopPoints": 30,
        "totalPoints": 44
      }
    },
    "set_number": 1,
    "time": 1646424120,
    "videos": [
      {
        "key": "6_Q90LtOaro",
        "type": "youtube"
      }
    ],
    "winning_alliance": "red"
  },
  {
    "actual_time": 1646428477,
    "alliances": {
      "blue": {
        "dq_team_keys": [],
        "score": 16,
        "surrogate_team_keys": [],
        "team_keys": [
          "frc1512",
          "frc811",
          "frc8708"
        ]
      },
      "red": {
        "dq_team_keys": [],
        "score": 7,
        "surrogate_team_keys": [],
        "team_keys": [
          "frc5491",
          "frc1247",
          "frc2262"
        ]
      }
    },
    "comp_level": "qm",
    "event_key": "2022nhgrs",
    "key": "2022nhgrs_qm31",
    "match_number": 31,
    "post_result_time": 1646428659,
    "predicted_time": 1646428622,
    "score_breakdown": {
      "blue": {
        "adjustPoints": 0,
        "autoCargoLowerBlue": 0,
        "autoCargoLowerFar": 0,
        "autoCargoLowerNear": 0,
        "autoCargoLowerRed": 1,
        "autoCargoPoints": 2,
        "autoCargoTotal": 1,
        "autoCargoUpperBlue": 0,
        "autoCargoUpperFar": 0,
        "autoCargoUpperNear": 0,
        "autoCargoUpperRed": 0,
        "autoPoints": 6,
        "autoTaxiPoints": 4,
        "cargoBonusRankingPoint": false,
        "endgamePoints": 6,
        "endgameRobot1": "Mid",
        "endgameRobot2": "None",
        "endgameRobot3": "None",
        "foulCount": 0,
        "foulPoints": 0,
        "hangarBonusRankingPoint": false,
        "matchCargoTotal": 3,
        "quintetAchieved": false,
        "rp": 2,
        "taxiRobot1": "Yes",
        "taxiRobot2": "Yes",
        "taxiRobot3": "No",
        "techFoulCount": 0,
        "teleopCargoLowerBlue": 0,
        "teleopCargoLowerFar": 0,
        "teleopCargoLowerNear": 0,
        "teleopCargoLowerRed": 0,
        "teleopCargoPoints": 4,
        "teleopCargoTotal": 2,
        "teleopCargoUpperBlue": 0,
        "teleopCargoUpperFar": 0,
        "teleopCargoUpperNear": 1,
        "teleopCargoUpperRed": 1,
        "teleopPoints": 10,
        "totalPoints": 16
      },
      "red": {
        "adjustPoints": 0,
        "autoCargoLowerBlue": 1,
        "autoCargoLowerFar": 0,
        "autoCargoLowerNear": 0,
        "autoCargoLowerRed": 0,
        "autoCargoPoints": 2,
        "autoCargoTotal": 1,
        "autoCargoUpperBlue": 0,
        "autoCargoUpperFar": 0,
        "autoCargoUpperNear": 0,
        "autoCargoUpperRed": 0,
        "autoPoints": 4,
        "autoTaxiPoints": 2,
        "cargoBonusRankingPoint": false,
        "endgamePoints": 0,
        "endgameRobot1": "None",
        "endgameRobot2": "None",
        "endgameRobot3": "None",
        "foulCount": 0,
        "foulPoints": 0,
        "hangarBonusRankingPoint": false,
        "matchCargoTotal": 4,
        "quintetAchieved": false,
        "rp": 0,
        "taxiRobot1": "No",
        "taxiRobot2": "Yes",
        "taxiRobot3": "No",
        "techFoulCount": 0,
        "teleopCargoLowerBlue": 1,
        "teleopCargoLowerFar": 0,
        "teleopCargoLowerNear": 1,
        "teleopCargoLowerRed": 1,
        "teleopCargoPoints": 3,
        "teleopCargoTotal": 3,
        "teleopCargoUpperBlue": 0,
        "teleopCargoUpperFar": 0,
        "teleopCargoUpperNear": 0,
        "teleopCargoUpperRed": 0,
        "teleopPoints": 3,
        "totalPoints": 7
      }
    },
    "set_number": 1,
    "time": 1646426640,
    "videos": [
      {
        "key": "zTH2yVL-d_k",
        "type": "youtube"
      }
    ],
    "winning_alliance": "blue"
  },
  {
    "actual_time": 1646431411,
    "alliances": {
      "blue": {
        "dq_team_keys": [],
        "score": 49,
        "surrogate_team_keys": [],
        "team_keys": [
          "frc5491",
          "frc3467",
          "frc1512"
        ]
      },
      "red": {
        "dq_team_keys": [],
        "score": 31,
        "surrogate_team_keys": [],
        "team_keys": [
          "frc5902",
          "frc4925",
          "frc8724"
        ]
      }
    },
    "comp_level": "qm",
    "event_key": "2022nhgrs",
    "key": "2022nhgrs_qm38",
    "match_number": 38,
    "post_result_time": 1646431605,
    "predicted_time": 1646431365,
    "score_breakdown": {
      "blue": {
        "adjustPoints": 0,
        "autoCargoLowerBlue": 0,
        "autoCargoLowerFar": 0,
        "autoCargoLowerNear": 0,
        "autoCargoLowerRed": 0,
        "autoCargoPoints": 4,
        "autoCargoTotal": 1,
        "autoCargoUpperBlue": 1,
        "autoCargoUpperFar": 0,
        "autoCargoUpperNear": 0,
        "autoCargoUpperRed": 0,
        "autoPoints": 8,
        "autoTaxiPoints": 4,
        "cargoBonusRankingPoint": false,
        "endgamePoints": 21,
        "endgameRobot1": "None",
        "endgameRobot2": "Traversal",
        "endgameRobot3": "Mid",
        "foulCount": 0,
        "foulPoints": 0,
        "hangarBonusRankingPoint": true,
        "matchCargoTotal": 12,
        "quintetAchieved": false,
        "rp": 3,
        "taxiRobot1": "No",
        "taxiRobot2": "Yes",
        "taxiRobot3": "Yes",
        "techFoulCount": 0,
        "teleopCargoLowerBlue": 0,
        "teleopCargoLowerFar": 0,
        "teleopCargoLowerNear": 2,
        "teleopCargoLowerRed": 0,
        "teleopCargoPoints": 20,
        "teleopCargoTotal": 11,
        "teleopCargoUpperBlue": 4,
        "teleopCargoUpperFar": 1,
        "teleopCargoUpperNear": 2,
        "teleopCargoUpperRed": 2,
        "teleopPoints": 41,
        "totalPoints": 49
      },
      "red": {
        "adjustPoints": 0,
        "autoCargoLowerBlue": 0,
        "autoCargoLowerFar": 0,
        "autoCargoLowerNear": 0,
        "autoCargoLowerRed": 0,
        "autoCargoPoints": 0,
        "autoCargoTotal": 0,
        "autoCargoUpperBlue": 0,
        "autoCargoUpperFar": 0,
        "autoCargoUpperNear": 0,
        "autoCargoUpperRed": 0,
        "autoPoints": 4,
        "autoTaxiPoints": 4,
        "cargoBonusRankingPoint": false,
        "endgamePoints": 6,
        "endgameRobot1": "Mid",
        "endgameRobot2": "None",
        "endgameRobot3": "None",
        "foulCount": 0,
        "foulPoints": 0,
        "hangarBonusRankingPoint": false,
        "matchCargoTotal": 11,
        "quintetAchieved": false,
        "rp": 0,
        "taxiRobot1": "Yes",
        "taxiRobot2": "No",
        "taxiRobot3": "Yes",
        "techFoulCount": 0,
        "teleopCargoLowerBlue": 1,
        "teleopCargoLowerFar": 0,
        "teleopCargoLowerNear": 0,
        "teleopCargoLowerRed": 0,
        "teleopCargoPoints": 21,
        "teleopCargoTotal": 11,
        "teleopCargoUpperBlue": 5,
        "teleopCargoUpperFar": 1,
        "teleopCargoUpperNear": 1,
        "teleopCargoUpperRed": 3,
        "teleopPoints": 27,
        "totalPoints": 31
      }
    },
    "set_number": 1,
    "time": 1646429580,
    "videos": [
      {
        "key": "Yfd_xYuyDtE",
        "type": "youtube"
      }
    ],
    "winning_alliance": "blue"
  },
  {
    "actual_time": 1646499188,
    "alliances": {
      "blue": {
        "dq_team_keys": [],
        "score": 57,
        "surrogate_team_keys": [],
        "team_keys": [
          "frc5491",
          "frc7407",
          "frc5902"
        ]
      },
      "red": {
        "dq_team_keys": [],
        "score": 17,
        "surrogate_team_keys": [],
        "team_keys": [
          "frc501",
          "frc1721",
          "frc1307"
        ]
      }
    },
    "comp_level": "qm",
    "event_key": "2022nhgrs",
    "key": "2022nhgrs_qm46",
    "match_number": 46,
    "post_result_time": 1646499460,
    "predicted_time": 1646435307,
    "score_breakdown": {
      "blue": {
        "adjustPoints": 0,
        "autoCargoLowerBlue": 0,
        "autoCargoLowerFar": 0,
        "autoCargoLowerNear": 0,
        "autoCargoLowerRed": 0,
        "autoCargoPoints": 16,
        "autoCargoTotal": 4,
        "autoCargoUpperBlue": 0,
        "autoCargoUpperFar": 0,
        "autoCargoUpperNear": 0,
        "autoCargoUpperRed": 4,
        "autoPoints": 20,
        "autoTaxiPoints": 4,
        "cargoBonusRankingPoint": false,
        "endgamePoints": 15,
        "endgameRobot1": "None",
        "endgameRobot2": "Traversal",
        "endgameRobot3": "None",
        "foulCount": 0,
        "foulPoints": 4,
        "hangarBonusRankingPoint": false,
        "matchCargoTotal": 13,
        "quintetAchieved": false,
        "rp": 2,
        "taxiRobot1": "No",
        "taxiRobot2": "Yes",
        "taxiRobot3": "Yes",
        "techFoulCount": 0,
        "teleopCargoLowerBlue": 0,
        "teleopCargoLowerFar": 0,
        "teleopCargoLowerNear": 0,
        "teleopCargoLowerRed": 0,
        "teleopCargoPoints": 18,
        "teleopCargoTotal": 9,
        "teleopCargoUpperBlue": 1,
        "teleopCargoUpperFar": 5,
        "teleopCargoUpperNear": 0,
        "teleopCargoUpperRed": 3,
        "teleopPoints": 33,
        "totalPoints": 57
      },
      "red": {
        "adjustPoints": 0,
        "autoCargoLowerBlue": 0,
        "autoCargoLowerFar": 0,
        "autoCargoLowerNear": 0,
        "autoCargoLowerRed": 1,
        "autoCargoPoints": 6,
        "autoCargoTotal": 2,
        "autoCargoUpperBlue": 0,
        "autoCargoUpperFar": 0,
        "autoCargoUpperNear": 1,
        "autoCargoUpperRed": 0,
        "autoPoints": 8,
        "autoTaxiPoints": 2,
        "cargoBonusRankingPoint": false,
        "endgamePoints": 0,
        "endgameRobot1": "None",
        "endgameRobot2": "None",
        "endgameRobot3": "None",
        "foulCount": 1,
        "foulPoints": 0,
        "hangarBonusRankingPoint": false,
        "matchCargoTotal": 9,
        "quintetAchieved": false,
        "rp": 0,
        "taxiRobot1": "No",
        "taxiRobot2": "No",
        "taxiRobot3": "Yes",
        "techFoulCount": 0,
        "teleopCargoLowerBlue": 1,
        "teleopCargoLowerFar": 1,
        "teleopCargoLowerNear": 2,
        "teleopCargoLowerRed": 1,
        "teleopCargoPoints": 9,
        "teleopCargoTotal": 7,
        "teleopCargoUpperBlue": 0,
        "teleopCargoUpperFar": 0,
        "teleopCargoUpperNear": 0,
        "teleopCargoUpperRed": 2,
        "teleopPoints": 9,
        "totalPoints": 17
      }
    },
    "set_number": 1,
    "time": 1646432940,
    "videos": [
      {
        "key": "SVr06Gb7kgs",
        "type": "youtube"
      }
    ],
    "winning_alliance": "blue"
  },
  {
    "actual_time": 1646412543,
    "alliances": {
      "blue": {
        "dq_team_keys": [],
        "score": 42,
        "surrogate_team_keys": [],
        "team_keys": [
          "frc8724",
          "frc8046",
          "frc1247"
        ]
      },
      "red": {
        "dq_team_keys": [],
        "score": 38,
        "surrogate_team_keys": [],
        "team_keys": [
          "frc78",
          "frc5491",
          "frc6690"
        ]
      }
    },
    "comp_level": "qm",
    "event_key": "2022nhgrs",
    "key": "2022nhgrs_qm5",
    "match_number": 5,
    "post_result_time": 1646412919,
    "predicted_time": 1646412472,
    "score_breakdown": {
      "blue": {
        "adjustPoints": 0,
        "autoCargoLowerBlue": 1,
        "autoCargoLowerFar": 0,
        "autoCargoLowerNear": 0,
        "autoCargoLowerRed": 0,
        "autoCargoPoints": 14,
        "autoCargoTotal": 4,
        "autoCargoUpperBlue": 1,
        "autoCargoUpperFar": 0,
        "autoCargoUpperNear": 1,
        "autoCargoUpperRed": 1,
        "autoPoints": 18,
        "autoTaxiPoints": 4,
        "cargoBonusRankingPoint": true,
        "endgamePoints": 0,
        "endgameRobot1": "None",
        "endgameRobot2": "None",
        "endgameRobot3": "None",
        "foulCount": 0,
        "foulPoints": 0,
        "hangarBonusRankingPoint": false,
        "matchCargoTotal": 21,
        "quintetAchieved": false,
        "rp": 3,
        "taxiRobot1": "Yes",
        "taxiRobot2": "Yes",
        "taxiRobot3": "No",
        "techFoulCount": 0,
        "teleopCargoLowerBlue": 6,
        "teleopCargoLowerFar": 2,
        "teleopCargoLowerNear": 1,
        "teleopCargoLowerRed": 1,
        "teleopCargoPoints": 24,
        "teleopCargoTotal": 17,
        "teleopCargoUpperBlue": 3,
        "teleopCargoUpperFar": 2,
        "teleopCargoUpperNear": 2,
        "teleopCargoUpperRed": 0,
        "teleopPoints": 24,
        "totalPoints": 42
      },
      "red": {
        "adjustPoints": 0,
        "autoCargoLowerBlue": 0,
        "autoCargoLowerFar": 1,
        "autoCargoLowerNear": 0,
        "autoCargoLowerRed": 0,
        "autoCargoPoints": 10,
        "autoCargoTotal": 3,
        "autoCargoUpperBlue": 0,
        "autoCargoUpperFar": 0,
        "autoCargoUpperNear": 1,
        "autoCargoUpperRed": 1,
        "autoPoints": 12,
        "autoTaxiPoints": 2,
        "cargoBonusRankingPoint": false,
        "endgamePoints": 12,
        "endgameRobot1": "Mid",
        "endgameRobot2": "None",
        "endgameRobot3": "Mid",
        "foulCount": 0,
        "foulPoints": 0,
        "hangarBonusRankingPoint": false,
        "matchCargoTotal": 10,
        "quintetAchieved": false,
        "rp": 0,
        "taxiRobot1": "Yes",
        "taxiRobot2": "No",
        "taxiRobot3": "No",
        "techFoulCount": 0,
        "teleopCargoLowerBlue": 0,
        "teleopCargoLowerFar": 0,
        "teleopCargoLowerNear": 0,
        "teleopCargoLowerRed": 0,
        "teleopCargoPoints": 14,
        "teleopCargoTotal": 7,
        "teleopCargoUpperBlue": 3,
        "teleopCargoUpperFar": 1,
        "teleopCargoUpperNear": 2,
        "teleopCargoUpperRed": 1,
        "teleopPoints": 26,
        "totalPoints": 38
      }
    },
    "set_number": 1,
    "time": 1646411520,
    "videos": [
      {
        "key": "_XfZzS2e1xE",
        "type": "youtube"
      }
    ],
    "winning_alliance": "blue"
  },
  {
    "actual_time": 1646437778,
    "alliances": {
      "blue": {
        "dq_team_keys": [],
        "score": 62,
        "surrogate_team_keys": [],
        "team_keys": [
          "frc4987",
          "frc126",
          "frc131"
        ]
      },
      "red": {
        "dq_team_keys": [],
        "score": 3,
        "surrogate_team_keys": [],
        "team_keys": [
          "frc5491",
          "frc1307",
          "frc4925"
        ]
      }
    },
    "comp_level": "qm",
    "event_key": "2022nhgrs",
    "key": "2022nhgrs_qm52",
    "match_number": 52,
    "post_result_time": 1646437963,
    "predicted_time": 1646437896,
    "score_breakdown": {
      "blue": {
        "adjustPoints": 0,
        "autoCargoLowerBlue": 0,
        "autoCargoLowerFar": 0,
        "autoCargoLowerNear": 0,
        "autoCargoLowerRed": 0,
        "autoCargoPoints": 4,
        "autoCargoTotal": 1,
        "autoCargoUpperBlue": 1,
        "autoCargoUpperFar": 0,
        "autoCargoUpperNear": 0,
        "autoCargoUpperRed": 0,
        "autoPoints": 10,
        "autoTaxiPoints": 6,
        "cargoBonusRankingPoint": true,
        "endgamePoints": 21,
        "endgameRobot1": "None",
        "endgameRobot2": "Mid",
        "endgameRobot3": "Traversal",
        "foulCount": 0,
        "foulPoints": 0,
        "hangarBonusRankingPoint": true,
        "matchCargoTotal": 28,
        "quintetAchieved": false,
        "rp": 4,
        "taxiRobot1": "Yes",
        "taxiRobot2": "Yes",
        "taxiRobot3": "Yes",
        "techFoulCount": 0,
        "teleopCargoLowerBlue": 4,
        "teleopCargoLowerFar": 8,
        "teleopCargoLowerNear": 5,
        "teleopCargoLowerRed": 6,
        "teleopCargoPoints": 31,
        "teleopCargoTotal": 27,
        "teleopCargoUpperBlue": 0,
        "teleopCargoUpperFar": 2,
        "teleopCargoUpperNear": 1,
        "teleopCargoUpperRed": 1,
        "teleopPoints": 52,
        "totalPoints": 62
      },
      "red": {
        "adjustPoints": 0,
        "autoCargoLowerBlue": 0,
        "autoCargoLowerFar": 0,
        "autoCargoLowerNear": 0,
        "autoCargoLowerRed": 0,
        "autoCargoPoints": 0,
        "autoCargoTotal": 0,
        "autoCargoUpperBlue": 0,
        "autoCargoUpperFar": 0,
        "autoCargoUpperNear": 0,
        "autoCargoUpperRed": 0,
        "autoPoints": 2,
        "autoTaxiPoints": 2,
        "cargoBonusRankingPoint": false,
        "endgamePoints": 0,
        "endgameRobot1": "None",
        "endgameRobot2": "None",
        "endgameRobot3": "None",
        "foulCount": 0,
        "foulPoints": 0,
        "hangarBonusRankingPoint": false,
        "matchCargoTotal": 1,
        "quintetAchieved": false,
        "rp": 0,
        "taxiRobot1": "Yes",
        "taxiRobot2": "No",
        "taxiRobot3": "No",
        "techFoulCount": 0,
        "teleopCargoLowerBlue": 0,
        "teleopCargoLowerFar": 0,
        "teleopCargoLowerNear": 0,
        "teleopCargoLowerRed": 1,
        "teleopCargoPoints": 1,
        "teleopCargoTotal": 1,
        "teleopCargoUpperBlue": 0,
        "teleopCargoUpperFar": 0,
        "teleopCargoUpperNear": 0,
        "teleopCargoUpperRed": 0,
        "teleopPoints": 1,
        "totalPoints": 3
      }
    },
    "set_number": 1,
    "time": 1646435460,
    "videos": [
      {
        "key": "5aY5IodkJHc",
        "type": "youtube"
      }
    ],
    "winning_alliance": "blue"
  },
  {
    "actual_time": 1646439902,
    "alliances": {
      "blue": {
        "dq_team_keys": [],
        "score": 62,
        "surrogate_team_keys": [],
        "team_keys": [
          "frc6328",
          "frc5491",
          "frc6762"
        ]
      },
      "red": {
        "dq_team_keys": [],
        "score": 7,
        "surrogate_team_keys": [],
        "team_keys": [
          "frc4761",
          "frc1721",
          "frc4987"
        ]
      }
    },
    "comp_level": "qm",
    "event_key": "2022nhgrs",
    "key": "2022nhgrs_qm57",
    "match_number": 57,
    "post_result_time": 1646440081,
    "predicted_time": 1646439871,
    "score_breakdown": {
      "blue": {
        "adjustPoints": 0,
        "autoCargoLowerBlue": 0,
        "autoCargoLowerFar": 0,
        "autoCargoLowerNear": 0,
        "autoCargoLowerRed": 0,
        "autoCargoPoints": 20,
        "autoCargoTotal": 5,
        "autoCargoUpperBlue": 0,
        "autoCargoUpperFar": 3,
        "autoCargoUpperNear": 0,
        "autoCargoUpperRed": 2,
        "autoPoints": 24,
        "autoTaxiPoints": 4,
        "cargoBonusRankingPoint": false,
        "endgamePoints": 16,
        "endgameRobot1": "High",
        "endgameRobot2": "None",
        "endgameRobot3": "Mid",
        "foulCount": 0,
        "foulPoints": 0,
        "hangarBonusRankingPoint": true,
        "matchCargoTotal": 16,
        "quintetAchieved": true,
        "rp": 3,
        "taxiRobot1": "Yes",
        "taxiRobot2": "No",
        "taxiRobot3": "Yes",
        "techFoulCount": 0,
        "teleopCargoLowerBlue": 0,
        "teleopCargoLowerFar": 0,
        "teleopCargoLowerNear": 0,
        "teleopCargoLowerRed": 0,
        "teleopCargoPoints": 22,
        "teleopCargoTotal": 11,
        "teleopCargoUpperBlue": 3,
        "teleopCargoUpperFar": 5,
        "teleopCargoUpperNear": 2,
        "teleopCargoUpperRed": 1,
        "teleopPoints": 38,
        "totalPoints": 62
      },
      "red": {
        "adjustPoints": 0,
        "autoCargoLowerBlue": 1,
        "autoCargoLowerFar": 0,
        "autoCargoLowerNear": 0,
        "autoCargoLowerRed": 0,
        "autoCargoPoints": 2,
        "autoCargoTotal": 1,
        "autoCargoUpperBlue": 0,
        "autoCargoUpperFar": 0,
        "autoCargoUpperNear": 0,
        "autoCargoUpperRed": 0,
        "autoPoints": 4,
        "autoTaxiPoints": 2,
        "cargoBonusRankingPoint": false,
        "endgamePoints": 0,
        "endgameRobot1": "None",
        "endgameRobot2": "None",
        "endgameRobot3": "None",
        "foulCount": 0,
        "foulPoints": 0,
        "hangarBonusRankingPoint": false,
        "matchCargoTotal": 3,
        "quintetAchieved": false,
        "rp": 0,
        "taxiRobot1": "Yes",
        "taxiRobot2": "No",
        "taxiRobot3": "No",
        "techFoulCount": 0,
        "teleopCargoLowerBlue": 0,
        "teleopCargoLowerFar": 0,
        "teleopCargoLowerNear": 1,
        "teleopCargoLowerRed": 0,
        "teleopCargoPoints": 3,
        "teleopCargoTotal": 2,
        "teleopCargoUpperBlue": 0,
        "teleopCargoUpperFar": 0,
        "teleopCargoUpperNear": 0,
        "teleopCargoUpperRed": 1,
        "teleopPoints": 3,
        "totalPoints": 7
      }
    },
    "set_number": 1,
    "time": 1646437560,
    "videos": [
      {
        "key": "T6_NGSOoUC4",
        "type": "youtube"
      }
    ],
    "winning_alliance": "blue"
  },
  {
    "actual_time": 1646490619,
    "alliances": {
      "blue": {
        "dq_team_keys": [],
        "score": 34,
        "surrogate_team_keys": [],
        "team_keys": [
          "frc3566",
          "frc663",
          "frc5491"
        ]
      },
      "red": {
        "dq_team_keys": [],
        "score": 41,
        "surrogate_team_keys": [],
        "team_keys": [
          "frc126",
          "frc5902",
          "frc88"
        ]
      }
    },
    "comp_level": "qm",
    "event_key": "2022nhgrs",
    "key": "2022nhgrs_qm61",
    "match_number": 61,
    "post_result_time": 1646490810,
    "predicted_time": 1646491080,
    "score_breakdown": {
      "blue": {
        "adjustPoints": 0,
        "autoCargoLowerBlue": 0,
        "autoCargoLowerFar": 0,
        "autoCargoLowerNear": 0,
        "autoCargoLowerRed": 0,
        "autoCargoPoints": 0,
        "autoCargoTotal": 0,
        "autoCargoUpperBlue": 0,
        "autoCargoUpperFar": 0,
        "autoCargoUpperNear": 0,
        "autoCargoUpperRed": 0,
        "autoPoints": 4,
        "autoTaxiPoints": 4,
        "cargoBonusRankingPoint": false,
        "endgamePoints": 0,
        "endgameRobot1": "None",
        "endgameRobot2": "None",
        "endgameRobot3": "None",
        "foulCount": 0,
        "foulPoints": 12,
        "hangarBonusRankingPoint": false,
        "matchCargoTotal": 10,
        "quintetAchieved": false,
        "rp": 0,
        "taxiRobot1": "Yes",
        "taxiRobot2": "Yes",
        "taxiRobot3": "No",
        "techFoulCount": 0,
        "teleopCargoLowerBlue": 1,
        "teleopCargoLowerFar": 0,
        "teleopCargoLowerNear": 1,
        "teleopCargoLowerRed": 0,
        "teleopCargoPoints": 18,
        "teleopCargoTotal": 10,
        "teleopCargoUpperBlue": 2,
        "teleopCargoUpperFar": 1,
        "teleopCargoUpperNear": 1,
        "teleopCargoUpperRed": 4,
        "teleopPoints": 18,
        "totalPoints": 34
      },
      "red": {
        "adjustPoints": 0,
        "autoCargoLowerBlue": 0,
        "autoCargoLowerFar": 0,
        "autoCargoLowerNear": 0,
        "autoCargoLowerRed": 0,
        "autoCargoPoints": 8,
        "autoCargoTotal": 2,
        "autoCargoUpperBlue": 1,
        "autoCargoUpperFar": 1,
        "autoCargoUpperNear": 0,
        "autoCargoUpperRed": 0,
        "autoPoints": 14,
        "autoTaxiPoints": 6,
        "cargoBonusRankingPoint": false,
        "endgamePoints": 0,
        "endgameRobot1": "None",
        "endgameRobot2": "None",
        "endgameRobot3": "None",
        "foulCount": 3,
        "foulPoints": 0,
        "hangarBonusRankingPoint": false,
        "matchCargoTotal": 17,
        "quintetAchieved": false,
        "rp": 2,
        "taxiRobot1": "Yes",
        "taxiRobot2": "Yes",
        "taxiRobot3": "Yes",
        "techFoulCount": 0,
        "teleopCargoLowerBlue": 1,
        "teleopCargoLowerFar": 1,
        "teleopCargoLowerNear": 0,
        "teleopCargoLowerRed": 1,
        "teleopCargoPoints": 27,
        "teleopCargoTotal": 15,
        "teleopCargoUpperBlue": 4,
        "teleopCargoUpperFar": 2,
        "teleopCargoUpperNear": 2,
        "teleopCargoUpperRed": 4,
        "teleopPoints": 27,
        "totalPoints": 41
      }
    },
    "set_number": 1,
    "time": 1646491080,
    "videos": [
      {
        "key": "kgeFFPorGzg",
        "type": "youtube"
      }
    ],
    "winning_alliance": "red"
  },
  {
    "actual_time": 1646492599,
    "alliances": {
      "blue": {
        "dq_team_keys": [],
        "score": 31,
        "surrogate_team_keys": [],
        "team_keys": [
          "frc1058",
          "frc5491",
          "frc8724"
        ]
      },
      "red": {
        "dq_team_keys": [],
        "score": 80,
        "surrogate_team_keys": [],
        "team_keys": [
          "frc1922",
          "frc7407",
          "frc811"
        ]
      }
    },
    "comp_level": "qm",
    "event_key": "2022nhgrs",
    "key": "2022nhgrs_qm66",
    "match_number": 66,
    "post_result_time": 1646492804,
    "predicted_time": 1646492821,
    "score_breakdown": {
      "blue": {
        "adjustPoints": 0,
        "autoCargoLowerBlue": 0,
        "autoCargoLowerFar": 0,
        "autoCargoLowerNear": 0,
        "autoCargoLowerRed": 0,
        "autoCargoPoints": 8,
        "autoCargoTotal": 2,
        "autoCargoUpperBlue": 1,
        "autoCargoUpperFar": 0,
        "autoCargoUpperNear": 1,
        "autoCargoUpperRed": 0,
        "autoPoints": 12,
        "autoTaxiPoints": 4,
        "cargoBonusRankingPoint": true,
        "endgamePoints": 0,
        "endgameRobot1": "None",
        "endgameRobot2": "None",
        "endgameRobot3": "None",
        "foulCount": 6,
        "foulPoints": 0,
        "hangarBonusRankingPoint": false,
        "matchCargoTotal": 21,
        "quintetAchieved": false,
        "rp": 1,
        "taxiRobot1": "Yes",
        "taxiRobot2": "No",
        "taxiRobot3": "Yes",
        "techFoulCount": 0,
        "teleopCargoLowerBlue": 3,
        "teleopCargoLowerFar": 2,
        "teleopCargoLowerNear": 8,
        "teleopCargoLowerRed": 6,
        "teleopCargoPoints": 19,
        "teleopCargoTotal": 19,
        "teleopCargoUpperBlue": 0,
        "teleopCargoUpperFar": 0,
        "teleopCargoUpperNear": 0,
        "teleopCargoUpperRed": 0,
        "teleopPoints": 19,
        "totalPoints": 31
      },
      "red": {
        "adjustPoints": 0,
        "autoCargoLowerBlue": 1,
        "autoCargoLowerFar": 0,
        "autoCargoLowerNear": 0,
        "autoCargoLowerRed": 0,
        "autoCargoPoints": 18,
        "autoCargoTotal": 5,
        "autoCargoUpperBlue": 2,
        "autoCargoUpperFar": 1,
        "autoCargoUpperNear": 1,
        "autoCargoUpperRed": 0,
        "autoPoints": 22,
        "autoTaxiPoints": 4,
        "cargoBonusRankingPoint": true,
        "endgamePoints": 10,
        "endgameRobot1": "None",
        "endgameRobot2": "Mid",
        "endgameRobot3": "Low",
        "foulCount": 0,
        "foulPoints": 24,
        "hangarBonusRankingPoint": false,
        "matchCargoTotal": 20,
        "quintetAchieved": true,
        "rp": 3,
        "taxiRobot1": "No",
        "taxiRobot2": "Yes",
        "taxiRobot3": "Yes",
        "techFoulCount": 0,
        "teleopCargoLowerBlue": 2,
        "teleopCargoLowerFar": 1,
        "teleopCargoLowerNear": 1,
        "teleopCargoLowerRed": 2,
        "teleopCargoPoints": 24,
        "teleopCargoTotal": 15,
        "teleopCargoUpperBlue": 1,
        "teleopCargoUpperFar": 1,
        "teleopCargoUpperNear": 4,
        "teleopCargoUpperRed": 3,
        "teleopPoints": 34,
        "totalPoints": 80
      }
    },
    "set_number": 1,
    "time": 1646493480,
    "videos": [
      {
        "key": "_3TjUldic1M",
        "type": "youtube"
      }
    ],
    "winning_alliance": "red"
  },
  {
    "actual_time": 1646495783,
    "alliances": {
      "blue": {
        "dq_team_keys": [],
        "score": 26,
        "surrogate_team_keys": [],
        "team_keys": [
          "frc6895",
          "frc5491",
          "frc811"
        ]
      },
      "red": {
        "dq_team_keys": [],
        "score": 41,
        "surrogate_team_keys": [],
        "team_keys": [
          "frc1729",
          "frc8046",
          "frc4909"
        ]
      }
    },
    "comp_level": "qm",
    "event_key": "2022nhgrs",
    "key": "2022nhgrs_qm74",
    "match_number": 74,
    "post_result_time": 1646495965,
    "predicted_time": 1646496420,
    "score_breakdown": {
      "blue": {
        "adjustPoints": 0,
        "autoCargoLowerBlue": 0,
        "autoCargoLowerFar": 0,
        "autoCargoLowerNear": 0,
        "autoCargoLowerRed": 0,
        "autoCargoPoints": 4,
        "autoCargoTotal": 1,
        "autoCargoUpperBlue": 0,
        "autoCargoUpperFar": 1,
        "autoCargoUpperNear": 0,
        "autoCargoUpperRed": 0,
        "autoPoints": 10,
        "autoTaxiPoints": 6,
        "cargoBonusRankingPoint": false,
        "endgamePoints": 6,
        "endgameRobot1": "None",
        "endgameRobot2": "None",
        "endgameRobot3": "Mid",
        "foulCount": 0,
        "foulPoints": 8,
        "hangarBonusRankingPoint": false,
        "matchCargoTotal": 2,
        "quintetAchieved": false,
        "rp": 0,
        "taxiRobot1": "Yes",
        "taxiRobot2": "Yes",
        "taxiRobot3": "Yes",
        "techFoulCount": 0,
        "teleopCargoLowerBlue": 0,
        "teleopCargoLowerFar": 0,
        "teleopCargoLowerNear": 0,
        "teleopCargoLowerRed": 0,
        "teleopCargoPoints": 2,
        "teleopCargoTotal": 1,
        "teleopCargoUpperBlue": 0,
        "teleopCargoUpperFar": 1,
        "teleopCargoUpperNear": 0,
        "teleopCargoUpperRed": 0,
        "teleopPoints": 8,
        "totalPoints": 26
      },
      "red": {
        "adjustPoints": 0,
        "autoCargoLowerBlue": 0,
        "autoCargoLowerFar": 0,
        "autoCargoLowerNear": 0,
        "autoCargoLowerRed": 0,
        "autoCargoPoints": 12,
        "autoCargoTotal": 3,
        "autoCargoUpperBlue": 1,
        "autoCargoUpperFar": 0,
        "autoCargoUpperNear": 0,
        "autoCargoUpperRed": 2,
        "autoPoints": 14,
        "autoTaxiPoints": 2,
        "cargoBonusRankingPoint": true,
        "endgamePoints": 0,
        "endgameRobot1": "None",
        "endgameRobot2": "None",
        "endgameRobot3": "None",
        "foulCount": 2,
        "foulPoints": 0,
        "hangarBonusRankingPoint": false,
        "matchCargoTotal": 20,
        "quintetAchieved": false,
        "rp": 3,
        "taxiRobot1": "Yes",
        "taxiRobot2": "No",
        "taxiRobot3": "No",
        "techFoulCount": 0,
        "teleopCargoLowerBlue": 2,
        "teleopCargoLowerFar": 2,
        "teleopCargoLowerNear": 1,
        "teleopCargoLowerRed": 2,
        "teleopCargoPoints": 27,
        "teleopCargoTotal": 17,
        "teleopCargoUpperBlue": 3,
        "teleopCargoUpperFar": 2,
        "teleopCargoUpperNear": 3,
        "teleopCargoUpperRed": 2,
        "teleopPoints": 27,
        "totalPoints": 41
      }
    },
    "set_number": 1,
    "time": 1646497320,
    "videos": [
      {
        "key": "C26jyCN4hRM",
        "type": "youtube"
      },
      {
        "key": "qNh-yxRmg5k",
        "type": "youtube"
      }
    ],
    "winning_alliance": "red"
  }
]